{"baseline_version":1,"record_count":22,"records":[{"display_name":"14th Street Corridor (3rd Ave to 9th Ave)","evidence_refs":[{"block_id":"p001_b0001","source_id":"14th_street_busway"}],"payload":{"borough":"Manhattan","borough_normalized":"manhattan","corridor_name":"14th Street Busway Corridor","days":"Daily","from":"3rd Avenue","hours":"6 AM to 10 PM","limits":"Between 3rd Avenue and 9th Avenue","local_access":"All other vehicles may make local trips to access businesses, residences and garages along 14th Street, but drivers must make the next available right turn.","street":"14th Street","through_access_vehicles":["buses","trucks","emergency vehicles"],"to":"9th Avenue"},"record_kind":"corridor","review_state":"unreviewed","truth_status":"source_stated","v1_record_id":"corridor_14th-street-ttp"},{"display_name":"NYC Department of Transportation","evidence_refs":[{"block_id":"p001_b0001","source_id":"14th_street_busway"}],"payload":{"acronym":"NYC DOT","entity_name":"New York City Department of Transportation","entity_type":"agency"},"record_kind":"entity","review_state":"unreviewed","truth_status":"source_stated","v1_record_id":"entity_12477929a987"},{"display_name":"New York City Police Department","evidence_refs":[{"block_id":"p001_b0001","source_id":"14th_street_busway"}],"payload":{"acronym":"NYPD","entity_name":"New York City Police Department","entity_type":"agency"},"record_kind":"entity","review_state":"unreviewed","truth_status":"source_stated","v1_record_id":"entity_9fea78f2e748"},{"display_name":"MTA New York City Transit","evidence_refs":[{"block_id":"p001_b0001","source_id":"14th_street_busway"}],"payload":{"acronym":"NYCT","entity_name":"MTA New York City Transit","entity_type":"agency","parent_organization":"MTA"},"record_kind":"entity","review_state":"unreviewed","truth_status":"source_stated","v1_record_id":"entity_c52d5a56b0fc"},{"display_name":"14th Street Busway Made Permanent","evidence_refs":[{"block_id":"p001_b0001","source_id":"14th_street_busway"}],"payload":{"date_normalized":"2020-06","date_precision":"month","date_text":"June 2020","date_text_normalized":{"confidence":"parsed_text","normalized_date":"2020-06","precision":"month","raw_text":"June 2020"},"description":"14th Street Busway was made permanent","event_date":"June 2020","event_date_normalized":{"confidence":"parsed_text","normalized_date":"2020-06","precision":"month","raw_text":"June 2020"},"event_family":"milestone","event_kind":"milestone","lifecycle_phase":"other","lifecycle_phase_other":"milestone"},"record_kind":"event","review_state":"unreviewed","truth_status":"source_stated","v1_record_id":"event_permanent"},{"display_name":"14th Street Transit and Truck Priority Pilot Launch","evidence_refs":[{"block_id":"p001_b0001","source_id":"14th_street_busway"}],"payload":{"date_normalized":"2019-10-03","date_precision":"day","date_text":"October 3, 2019","date_text_normalized":{"confidence":"parsed_text","normalized_date":"2019-10-03","precision":"day","raw_text":"October 3, 2019"},"description":"14th Street Transit and Truck Priority Pilot Project began","event_date":"October 3, 2019","event_date_normalized":{"confidence":"parsed_text","normalized_date":"2019-10-03","precision":"day","raw_text":"October 3, 2019"},"event_family":"launch","event_kind":"launch","lifecycle_phase":"launched"},"record_kind":"event","review_state":"unreviewed","truth_status":"source_stated","v1_record_id":"event_pilot_start"},{"display_name":"M14A/D Select Bus Service Launch","evidence_refs":[{"block_id":"p001_b0001","source_id":"14th_street_busway"}],"payload":{"date_normalized":"2019-07-01","date_precision":"day","date_text":"July 1, 2019","date_text_normalized":{"confidence":"parsed_text","normalized_date":"2019-07-01","precision":"day","raw_text":"July 1, 2019"},"description":"M14A/D Select Bus Service began","event_date":"July 1, 2019","event_date_normalized":{"confidence":"parsed_text","normalized_date":"2019-07-01","precision":"day","raw_text":"July 1, 2019"},"event_family":"launch","event_kind":"launch","lifecycle_phase":"launched"},"record_kind":"event","review_state":"unreviewed","truth_status":"source_stated","v1_record_id":"event_sbs_launch"},{"display_name":"M14 Daily Ridership","evidence_refs":[{"block_id":"p001_b0001","source_id":"14th_street_busway"}],"payload":{"metric_name":"daily_ridership","period":"daily","raw_value_text":"approximately 28,000 daily M14 riders","scope":"M14 route","unit":"riders","unit_normalized":{"normalized_unit":"riders","raw_text":"riders","unit_family":"ridership"},"value":28000},"record_kind":"metric_claim","review_state":"unreviewed","truth_status":"source_stated","v1_record_id":"metric_daily_ridership"},{"display_name":"14th Street Busway Bus Speed Increase","evidence_refs":[{"block_id":"p001_b0001","source_id":"14th_street_busway"}],"payload":{"direction":"increase","direction_normalized":{"normalized_value":"increase","raw_text":"increase"},"metric_name":"bus_speed_increase","raw_value_text":"up to 24%","scope":"14th Street busway","unit":"percent","unit_normalized":{"normalized_unit":"percent","raw_text":"percent","unit_family":"percentage"},"value":24},"record_kind":"metric_claim","review_state":"unreviewed","truth_status":"source_stated","v1_record_id":"metric_speed_increase"},{"display_name":"14th Street Busway","evidence_refs":[{"block_id":"p001_b0001","source_id":"14th_street_busway"}],"payload":{"borough":"Manhattan","borough_normalized":"manhattan","completion_date":"June 2020","completion_date_normalized":{"confidence":"parsed_text","normalized_date":"2020-06","precision":"month","raw_text":"June 2020"},"daily_ridership":28000,"date_normalized":"2020-06","date_precision":"month","date_source_field":"completion_date","description":"14th Street Busway with transit and truck priority, left turn restrictions, and dedicated bus lanes from 9th Avenue to 1st Avenue.","document_time_status":"implemented","launch_date":"October 3, 2019","launch_date_normalized":{"confidence":"parsed_text","normalized_date":"2019-10-03","precision":"day","raw_text":"October 3, 2019"},"lead_agency":"NYC DOT","name":"14th Street Busway","partner_agency":"MTA New York City Transit","project_family":"sbs_or_brt","project_name":"14th Street Busway","project_type":"Bus Rapid Transit - 14th Street Select Bus Service with Transit & Truck Priority Pilot Project","routes_served":["M14A/D"],"status":"made permanent"},"record_kind":"project","review_state":"unreviewed","truth_status":"source_stated","v1_record_id":"project_14th-street-busway-permanent"},{"display_name":"14th Street Busway timeline: made permanent","evidence_refs":[{"block_id":"p001_b0001","source_id":"14th_street_busway"}],"payload":{"object_id":"event_permanent","object_local_observation_id":"event_permanent","relation_family":"timeline_context","relation_kind":"has_timeline_event","subject_id":"project_14th-street-busway-permanent","subject_local_observation_id":"proj_14th_st_busway"},"record_kind":"relation","relation":{"object_id":"event_permanent","relation_family":"timeline_context","relation_kind":"has_timeline_event","subject_id":"project_14th-street-busway-permanent"},"review_state":"unreviewed","truth_status":"source_stated","v1_record_id":"rel_proj_event_perm"},{"display_name":"14th Street Busway timeline: pilot start","evidence_refs":[{"block_id":"p001_b0001","source_id":"14th_street_busway"}],"payload":{"object_id":"event_pilot_start","object_local_observation_id":"event_pilot_start","relation_family":"timeline_context","relation_kind":"has_timeline_event","subject_id":"project_14th-street-busway-permanent","subject_local_observation_id":"proj_14th_st_busway"},"record_kind":"relation","relation":{"object_id":"event_pilot_start","relation_family":"timeline_context","relation_kind":"has_timeline_event","subject_id":"project_14th-street-busway-permanent"},"review_state":"unreviewed","truth_status":"source_stated","v1_record_id":"rel_proj_event_pilot"},{"display_name":"14th Street Busway implemented by NYC DOT","evidence_refs":[{"block_id":"p001_b0001","source_id":"14th_street_busway"}],"payload":{"object_id":"entity_12477929a987","object_local_observation_id":"ent_nyc_dot","relation_family":"agency_role","relation_kind":"implemented_by","subject_id":"project_14th-street-busway-permanent","subject_local_observation_id":"proj_14th_st_busway"},"record_kind":"relation","relation":{"object_id":"entity_12477929a987","relation_family":"agency_role","relation_kind":"implemented_by","subject_id":"project_14th-street-busway-permanent"},"review_state":"unreviewed","truth_status":"source_stated","v1_record_id":"rel_proj_impl_dot"},{"display_name":"14th Street Busway implemented by MTA NYCT","evidence_refs":[{"block_id":"p001_b0001","source_id":"14th_street_busway"}],"payload":{"object_id":"entity_c52d5a56b0fc","object_local_observation_id":"ent_mta_nyct","relation_family":"agency_role","relation_kind":"implemented_by","subject_id":"project_14th-street-busway-permanent","subject_local_observation_id":"proj_14th_st_busway"},"record_kind":"relation","relation":{"object_id":"entity_c52d5a56b0fc","relation_family":"agency_role","relation_kind":"implemented_by","subject_id":"project_14th-street-busway-permanent"},"review_state":"unreviewed","truth_status":"source_stated","v1_record_id":"rel_proj_impl_mta"},{"display_name":"14th Street Busway has bus speed increase metric","evidence_refs":[{"block_id":"p001_b0001","source_id":"14th_street_busway"}],"payload":{"object_id":"metric_speed_increase","object_local_observation_id":"metric_speed_increase","relation_family":"metric_context","relation_kind":"has_metric","subject_id":"project_14th-street-busway-permanent","subject_local_observation_id":"proj_14th_st_busway"},"record_kind":"relation","relation":{"object_id":"metric_speed_increase","relation_family":"metric_context","relation_kind":"has_metric","subject_id":"project_14th-street-busway-permanent"},"review_state":"unreviewed","truth_status":"source_stated","v1_record_id":"rel_proj_metric_speed"},{"display_name":"14th Street Busway has treatment","evidence_refs":[{"block_id":"p001_b0001","source_id":"14th_street_busway"}],"payload":{"object_id":"treat_14th_st_busway","object_local_observation_id":"treat_14th_st_busway","relation_family":"treatment_context","relation_kind":"has_treatment","subject_id":"project_14th-street-busway-permanent","subject_local_observation_id":"proj_14th_st_busway"},"record_kind":"relation","relation":{"object_id":"treat_14th_st_busway","relation_family":"treatment_context","relation_kind":"has_treatment","subject_id":"project_14th-street-busway-permanent"},"review_state":"unreviewed","truth_status":"source_stated","v1_record_id":"rel_proj_treat"},{"display_name":"M14A/D operates on 14th Street corridor","evidence_refs":[{"block_id":"p001_b0001","source_id":"14th_street_busway"}],"payload":{"object_id":"corridor_14th-street-ttp","object_local_observation_id":"corr_14th_st_3rd_to_9th","relation_family":"corridor_scope","relation_kind":"operates_on_corridor","subject_id":"route_m14-ad-sbs","subject_local_observation_id":"route_m14ad"},"record_kind":"relation","relation":{"object_id":"corridor_14th-street-ttp","relation_family":"corridor_scope","relation_kind":"operates_on_corridor","subject_id":"route_m14-ad-sbs"},"review_state":"unreviewed","truth_status":"source_stated","v1_record_id":"rel_route_corr"},{"display_name":"M14A/D has daily ridership metric","evidence_refs":[{"block_id":"p001_b0001","source_id":"14th_street_busway"}],"payload":{"object_id":"metric_daily_ridership","object_local_observation_id":"metric_daily_ridership","relation_family":"metric_context","relation_kind":"has_metric","subject_id":"route_m14-ad-sbs","subject_local_observation_id":"route_m14ad"},"record_kind":"relation","relation":{"object_id":"metric_daily_ridership","relation_family":"metric_context","relation_kind":"has_metric","subject_id":"route_m14-ad-sbs"},"review_state":"unreviewed","truth_status":"source_stated","v1_record_id":"rel_route_metric_ridership"},{"display_name":"M14A/D operated by NYCT","evidence_refs":[{"block_id":"p001_b0001","source_id":"14th_street_busway"}],"payload":{"object_id":"entity_c52d5a56b0fc","object_local_observation_id":"ent_mta_nyct","relation_family":"agency_role","relation_kind":"operated_by","subject_id":"route_m14-ad-sbs","subject_local_observation_id":"route_m14ad"},"record_kind":"relation","relation":{"object_id":"entity_c52d5a56b0fc","relation_family":"agency_role","relation_kind":"operated_by","subject_id":"route_m14-ad-sbs"},"review_state":"unreviewed","truth_status":"source_stated","v1_record_id":"rel_route_op_mta"},{"display_name":"M14A/D Select Bus Service","evidence_refs":[{"block_id":"p001_b0001","source_id":"14th_street_busway"}],"payload":{"agency":"MTA New York City Transit","borough":"Manhattan","borough_normalized":"manhattan","program":"Select Bus Service","route_id":"M14A/D","route_label":"M14A/D-SBS","route_name":"M14A/D Select Bus Service","route_type":"Select Bus Service","route_type_normalized":"select_bus_service","service_variant":"sbs","streets":"14th Street"},"record_kind":"route","review_state":"unreviewed","truth_status":"source_stated","v1_record_id":"route_m14-ad-sbs"},{"display_name":"14th Street Busway Webpage","evidence_refs":[{"block_id":"p001_b0001","source_id":"14th_street_busway"}],"payload":{"content_type":"webpage","description":"NYC DOT page describing the 14th Street Busway, its rules, background, and community outreach.","publisher":"NYC DOT","title":"Bus Rapid Transit - 14th Street Select Bus Service with Transit & Truck Priority Pilot Project"},"record_kind":"source","review_state":"unreviewed","truth_status":"source_stated","v1_record_id":"src_14th_st_busway_page"},{"display_name":"14th Street Busway","evidence_refs":[{"block_id":"p001_b0001","source_id":"14th_street_busway"}],"payload":{"date_text":"October 3, 2019 pilot start","date_text_normalized":{"confidence":"parsed_text","normalized_date":"2019-10-03","precision":"day","raw_text":"October 3, 2019 pilot start"},"description":"Exclusive bus and truck lanes with left turn restrictions, automated enforcement, and local access rules.","enforcement_authority":"NYPD traffic agents and automated cameras","location_text":"14th Street between 3rd Avenue and 9th Avenue","normalized_location":{"cross_street":"Ninth Avenue","raw_text":"14th Street between 3rd Avenue and 9th Avenue","street":"14th Street"},"treatment_family":"busway","treatment_kind":"busway"},"record_kind":"treatment_component","review_state":"unreviewed","truth_status":"source_stated","v1_record_id":"treat_14th_st_busway"}],"release_id":"v1-rc5","source_id":"14th_street_busway"}
